ambientika/__init__.py
ambientika-0.0.3.dist-info/METADATA
ambientika-0.0.3.dist-info/WHEEL
ambientika-0.0.3.dist-info/licenses/LICENSE
ambientika-0.0.3.dist-info/RECORD
