Metadata-Version: 2.1
Name: ambientika
Version: 0.0.3
Summary: An API wrapper for Ambientika smart devices
Project-URL: Homepage, https://github.com/wingertge/ambientika-py
Project-URL: Issues, https://github.com/wingertge/ambientika-py/issues
Author-email: Genna Wingert <wingertge@gmail.com>
License-File: LICENSE
Classifier: License :: OSI Approved :: MIT License
Classifier: Operating System :: OS Independent
Classifier: Programming Language :: Python :: 3
Requires-Python: >=3.11
Requires-Dist: aiohttp
